optimus_prompt/__init__.py
optimus_prompt/core/__init__.py
optimus_prompt/core/prompt.py
optimus_prompt/core/response.py
optimus_prompt/core/writer.py
optimus_prompt/output/__init__.py
optimus_prompt/providers/__init__.py
optimus_prompt/providers/anthropic_provider.py
optimus_prompt/providers/base_provider.py
optimus_prompt/providers/openai_provider.py
optimus_prompt-0.1.0.dist-info/METADATA
optimus_prompt-0.1.0.dist-info/WHEEL
optimus_prompt-0.1.0.dist-info/RECORD
