Metadata-Version: 2.1
Name: optimus-prompt
Version: 0.1.0
Summary: Compare responses from different LLMs to the same prompt
License: MIT
Author: Craig
Requires-Python: >=3.9,<4.0
Classifier: License :: OSI Approved :: MIT License
Classifier: Programming Language :: Python :: 3
Classifier: Programming Language :: Python :: 3.9
Classifier: Programming Language :: Python :: 3.10
Classifier: Programming Language :: Python :: 3.11
Classifier: Programming Language :: Python :: 3.12
Requires-Dist: anthropic (>=0.8.0)
Requires-Dist: dotenv (>=0.9.9,<0.10.0)
Requires-Dist: openai (>=1.0.0,<2.0.0)
Requires-Dist: pydantic (>=2.0.0,<3.0.0)
Requires-Dist: python-dotenv (>=1.0.0,<2.0.0)
